{"services": [{"url": "http://status.mongohq.com/api/v1/services/aaron", "id": "aaron", "description": "MongoDB Server", "name": "Aaron", "current-event": {"status": {"description": "The service is up", "level": "NORMAL", "url": "http://status.mongohq.com/api/v1/statuses/up", "image": "http://status.mongohq.com/images/status/tick-circle.png", "id": "up", "name": "Up"}, "url": "http://status.mongohq.com/api/v1/services/aaron/events/ag5tb25nb2hxLXN0YXR1c3INCxIFRXZlbnQYi-gUDA", "timestamp": "Wed, 13 Mar 2013 18:10:21 GMT", "sid": "ag5tb25nb2hxLXN0YXR1c3INCxIFRXZlbnQYi-gUDA", "message": "All systems operational.", "informational": false}}, {"url": "http://status.mongohq.com/api/v1/services/alex", "id": "alex", "description": "A sandbox environment for MongoHQ.", "name": "Alex", "current-event": {"status": {"description": "The service is up", "level": "NORMAL", "url": "http://status.mongohq.com/api/v1/statuses/up", "image": "http://status.mongohq.com/images/status/tick-circle.png", "id": "up", "name": "Up"}, "url": "http://status.mongohq.com/api/v1/services/alex/events/ag5tb25nb2hxLXN0YXR1c3INCxIFRXZlbnQY0coWDA", "timestamp": "Sat, 20 Apr 2013 15:23:20 GMT", "sid": "ag5tb25nb2hxLXN0YXR1c3INCxIFRXZlbnQY0coWDA", "message": "Alex is operational.", "informational": false}}, {"url": "http://status.mongohq.com/api/v1/services/arrow", "id": "arrow", "description": "MongoDB Server", "name": "Arrow", "current-event": {"status": {"description": "The service is up", "level": "NORMAL", "url": "http://status.mongohq.com/api/v1/statuses/up", "image": "http://status.mongohq.com/images/status/tick-circle.png", "id": "up", "name": "Up"}, "url": "http://status.mongohq.com/api/v1/services/arrow/events/ag5tb25nb2hxLXN0YXR1c3INCxIFRXZlbnQYgtYNDA", "timestamp": "Sat, 30 Jun 2012 10:27:40 GMT", "sid": "ag5tb25nb2hxLXN0YXR1c3INCxIFRXZlbnQYgtYNDA", "message": "All databases accessible and operating normally.", "informational": false}}, {"url": "http://status.mongohq.com/api/v1/services/arzt", "id": "arzt", "description": "MongoDB Server", "name": "Arzt", "current-event": {"status": {"description": "The service is up", "level": "NORMAL", "url": "http://status.mongohq.com/api/v1/statuses/up", "image": "http://status.mongohq.com/images/status/tick-circle.png", "id": "up", "name": "Up"}, "url": "http://status.mongohq.com/api/v1/services/arzt/events/ag5tb25nb2hxLXN0YXR1c3INCxIFRXZlbnQY0cQYDA", "timestamp": "Sat, 18 May 2013 04:40:19 GMT", "sid": "ag5tb25nb2hxLXN0YXR1c3INCxIFRXZlbnQY0cQYDA", "message": "All mongo processes on arzt are fully available", "informational": false}}, {"url": "http://status.mongohq.com/api/v1/services/ben", "id": "ben", "description": "A MongoHQ Replica Set Small database environment.", "name": "Ben", "current-event": {"status": {"description": "The service is up", "level": "NORMAL", "url": "http://status.mongohq.com/api/v1/statuses/up", "image": "http://status.mongohq.com/images/status/tick-circle.png", "id": "up", "name": "Up"}, "url": "http://status.mongohq.com/api/v1/services/ben/events/ag5tb25nb2hxLXN0YXR1c3INCxIFRXZlbnQYsbcSDA", "timestamp": "Thu, 15 Nov 2012 22:07:29 GMT", "sid": "ag5tb25nb2hxLXN0YXR1c3INCxIFRXZlbnQYsbcSDA", "message": "Replica set is fully healthy now.", "informational": false}}, {"url": "http://status.mongohq.com/api/v1/services/bernard", "id": "bernard", "description": "MongoDB Server", "name": "Bernard", "current-event": {"status": {"description": "The service is up", "level": "NORMAL", "url": "http://status.mongohq.com/api/v1/statuses/up", "image": "http://status.mongohq.com/images/status/tick-circle.png", "id": "up", "name": "Up"}, "url": "http://status.mongohq.com/api/v1/services/bernard/events/ag5tb25nb2hxLXN0YXR1c3INCxIFRXZlbnQY8oQODA", "timestamp": "Sat, 30 Jun 2012 10:53:20 GMT", "sid": "ag5tb25nb2hxLXN0YXR1c3INCxIFRXZlbnQY8oQODA", "message": "grep Assert /mnt/log/mongodb/instance_*.log | cut -f1 -d: | sort | uniq | cut -d\"_\" -f2 | cut -d\".\" -f1", "informational": false}}, {"url": "http://status.mongohq.com/api/v1/services/blackrock", "id": "blackrock", "description": "MongoDB Server", "name": "BlackRock", "current-event": {"status": {"description": "The service is up", "level": "NORMAL", "url": "http://status.mongohq.com/api/v1/statuses/up", "image": "http://status.mongohq.com/images/status/tick-circle.png", "id": "up", "name": "Up"}, "url": "http://status.mongohq.com/api/v1/services/blackrock/events/ag5tb25nb2hxLXN0YXR1c3INCxIFRXZlbnQY69ERDA", "timestamp": "Mon, 22 Oct 2012 23:47:08 GMT", "sid": "ag5tb25nb2hxLXN0YXR1c3INCxIFRXZlbnQY69ERDA", "message": "Blackrock environment is fully recovered, secondary members are all online.", "informational": false}}, {"url": "http://status.mongohq.com/api/v1/services/boone", "id": "boone", "description": "MongoDB Server", "name": "Boone", "current-event": {"status": {"description": "The service is up", "level": "NORMAL", "url": "http://status.mongohq.com/api/v1/statuses/up", "image": "http://status.mongohq.com/images/status/tick-circle.png", "id": "up", "name": "Up"}, "url": "http://status.mongohq.com/api/v1/services/boone/events/ag5tb25nb2hxLXN0YXR1c3INCxIFRXZlbnQYybgPDA", "timestamp": "Wed, 19 Sep 2012 00:10:38 GMT", "sid": "ag5tb25nb2hxLXN0YXR1c3INCxIFRXZlbnQYybgPDA", "message": "Environment is running smoothly.", "informational": false}}, {"url": "http://status.mongohq.com/api/v1/services/candidate", "id": "candidate", "description": "Replica Set SSD.", "name": "Candidate", "current-event": {"status": {"description": "The service is up", "level": "NORMAL", "url": "http://status.mongohq.com/api/v1/statuses/up", "image": "http://status.mongohq.com/images/status/tick-circle.png", "id": "up", "name": "Up"}, "url": "http://status.mongohq.com/api/v1/services/candidate/events/ag5tb25nb2hxLXN0YXR1c3INCxIFRXZlbnQY8eYXDA", "timestamp": "Wed, 08 May 2013 07:50:12 GMT", "sid": "ag5tb25nb2hxLXN0YXR1c3INCxIFRXZlbnQY8eYXDA", "message": "candidate.1 connectivity restored", "informational": false}}, {"url": "http://status.mongohq.com/api/v1/services/charlotte", "id": "charlotte", "description": "MongoHQ shared large environment.", "name": "Charlotte", "current-event": {"status": {"description": "The service is up", "level": "NORMAL", "url": "http://status.mongohq.com/api/v1/statuses/up", "image": "http://status.mongohq.com/images/status/tick-circle.png", "id": "up", "name": "Up"}, "url": "http://status.mongohq.com/api/v1/services/charlotte/events/ag5tb25nb2hxLXN0YXR1c3INCxIFRXZlbnQYudsTDA", "timestamp": "Sun, 27 Jan 2013 16:26:44 GMT", "sid": "ag5tb25nb2hxLXN0YXR1c3INCxIFRXZlbnQYudsTDA", "message": "Charlotte is operating normally. We are running system checks now.", "informational": false}}, {"url": "http://status.mongohq.com/api/v1/services/claire", "id": "claire", "description": "MongoDB Server", "name": "Claire", "current-event": {"status": {"description": "The service is up", "level": "NORMAL", "url": "http://status.mongohq.com/api/v1/statuses/up", "image": "http://status.mongohq.com/images/status/tick-circle.png", "id": "up", "name": "Up"}, "url": "http://status.mongohq.com/api/v1/services/claire/events/ag5tb25nb2hxLXN0YXR1c3INCxIFRXZlbnQY0dwQDA", "timestamp": "Fri, 12 Oct 2012 01:01:46 GMT", "sid": "ag5tb25nb2hxLXN0YXR1c3INCxIFRXZlbnQY0dwQDA", "message": "Instance is healthy and service to DBs is being restored.", "informational": false}}, {"url": "http://status.mongohq.com/api/v1/services/desmond", "id": "desmond", "description": "EU West Replica Set.", "name": "Desmond", "current-event": null}, {"url": "http://status.mongohq.com/api/v1/services/dharma", "id": "dharma", "description": "MongoDB Sandbox service.", "name": "Dharma", "current-event": null}, {"url": "http://status.mongohq.com/api/v1/services/eko", "id": "eko", "description": "eko.mongohq.com", "name": "Eko", "current-event": {"status": {"description": "The service is up", "level": "NORMAL", "url": "http://status.mongohq.com/api/v1/statuses/up", "image": "http://status.mongohq.com/images/status/tick-circle.png", "id": "up", "name": "Up"}, "url": "http://status.mongohq.com/api/v1/services/eko/events/ag5tb25nb2hxLXN0YXR1c3INCxIFRXZlbnQYioANDA", "timestamp": "Fri, 15 Jun 2012 09:26:49 GMT", "sid": "ag5tb25nb2hxLXN0YXR1c3INCxIFRXZlbnQYioANDA", "message": "All systems are operational.", "informational": false}}, {"url": "http://status.mongohq.com/api/v1/services/ethan", "id": "ethan", "description": "MongoHQ Database service.", "name": "Ethan", "current-event": null}, {"url": "http://status.mongohq.com/api/v1/services/faraday", "id": "faraday", "description": "MongoDB Server", "name": "Faraday", "current-event": {"status": {"description": "The service is up", "level": "NORMAL", "url": "http://status.mongohq.com/api/v1/statuses/up", "image": "http://status.mongohq.com/images/status/tick-circle.png", "id": "up", "name": "Up"}, "url": "http://status.mongohq.com/api/v1/services/faraday/events/ag5tb25nb2hxLXN0YXR1c3INCxIFRXZlbnQYqYQWDA", "timestamp": "Mon, 15 Apr 2013 22:11:25 GMT", "sid": "ag5tb25nb2hxLXN0YXR1c3INCxIFRXZlbnQYqYQWDA", "message": "Maintenance has been completed. All systems are operational.", "informational": false}}, {"url": "http://status.mongohq.com/api/v1/services/flame", "id": "flame", "description": "MongoDB Server", "name": "Flame", "current-event": {"status": {"description": "The service is up", "level": "NORMAL", "url": "http://status.mongohq.com/api/v1/statuses/up", "image": "http://status.mongohq.com/images/status/tick-circle.png", "id": "up", "name": "Up"}, "url": "http://status.mongohq.com/api/v1/services/flame/events/ag5tb25nb2hxLXN0YXR1c3INCxIFRXZlbnQY6b8XDA", "timestamp": "Thu, 02 May 2013 03:56:49 GMT", "sid": "ag5tb25nb2hxLXN0YXR1c3INCxIFRXZlbnQY6b8XDA", "message": "Environment is fully up and healthy.", "informational": false}}, {"url": "http://status.mongohq.com/api/v1/services/heroku-addon", "id": "heroku-addon", "description": "AddOn component for Heroku", "name": "Heroku AddOn", "current-event": {"status": {"description": "The service is up", "level": "NORMAL", "url": "http://status.mongohq.com/api/v1/statuses/up", "image": "http://status.mongohq.com/images/status/tick-circle.png", "id": "up", "name": "Up"}, "url": "http://status.mongohq.com/api/v1/services/heroku-addon/events/ag5tb25nb2hxLXN0YXR1c3INCxIFRXZlbnQY6-kJDA", "timestamp": "Thu, 15 Dec 2011 07:27:02 GMT", "sid": "ag5tb25nb2hxLXN0YXR1c3INCxIFRXZlbnQY6-kJDA", "message": "All systems normal.", "informational": false}}, {"url": "http://status.mongohq.com/api/v1/services/hurley", "id": "hurley", "description": "MongoDB Server", "name": "Hurley", "current-event": {"status": {"description": "The service is up", "level": "NORMAL", "url": "http://status.mongohq.com/api/v1/statuses/up", "image": "http://status.mongohq.com/images/status/tick-circle.png", "id": "up", "name": "Up"}, "url": "http://status.mongohq.com/api/v1/services/hurley/events/ag5tb25nb2hxLXN0YXR1c3INCxIFRXZlbnQYyaAXDA", "timestamp": "Tue, 30 Apr 2013 05:14:06 GMT", "sid": "ag5tb25nb2hxLXN0YXR1c3INCxIFRXZlbnQYyaAXDA", "message": "Work on secondary member of cluster is now complete. ", "informational": false}}, {"url": "http://status.mongohq.com/api/v1/services/hydra", "id": "hydra", "description": "MongoDB Server", "name": "Hydra", "current-event": {"status": {"description": "The service is up", "level": "NORMAL", "url": "http://status.mongohq.com/api/v1/statuses/up", "image": "http://status.mongohq.com/images/status/tick-circle.png", "id": "up", "name": "Up"}, "url": "http://status.mongohq.com/api/v1/services/hydra/events/ag5tb25nb2hxLXN0YXR1c3INCxIFRXZlbnQYkaEPDA", "timestamp": "Sat, 25 Aug 2012 01:07:11 GMT", "sid": "ag5tb25nb2hxLXN0YXR1c3INCxIFRXZlbnQYkaEPDA", "message": "Systems operational.", "informational": false}}, {"url": "http://status.mongohq.com/api/v1/services/jack", "id": "jack", "description": "Large single-instance shared server.", "name": "Jack", "current-event": {"status": {"description": "The service is up", "level": "NORMAL", "url": "http://status.mongohq.com/api/v1/statuses/up", "image": "http://status.mongohq.com/images/status/tick-circle.png", "id": "up", "name": "Up"}, "url": "http://status.mongohq.com/api/v1/services/jack/events/ag5tb25nb2hxLXN0YXR1c3INCxIFRXZlbnQYkYkXDA", "timestamp": "Sat, 27 Apr 2013 05:26:48 GMT", "sid": "ag5tb25nb2hxLXN0YXR1c3INCxIFRXZlbnQYkYkXDA", "message": "Environment is back online", "informational": false}}, {"url": "http://status.mongohq.com/api/v1/services/jin", "id": "jin", "description": "A Replica Set Small environment.", "name": "Jin", "current-event": {"status": {"description": "The service is up", "level": "NORMAL", "url": "http://status.mongohq.com/api/v1/statuses/up", "image": "http://status.mongohq.com/images/status/tick-circle.png", "id": "up", "name": "Up"}, "url": "http://status.mongohq.com/api/v1/services/jin/events/ag5tb25nb2hxLXN0YXR1c3INCxIFRXZlbnQYie4SDA", "timestamp": "Thu, 03 Jan 2013 22:29:36 GMT", "sid": "ag5tb25nb2hxLXN0YXR1c3INCxIFRXZlbnQYie4SDA", "message": "All systems operational.", "informational": false}}, {"url": "http://status.mongohq.com/api/v1/services/juliet", "id": "juliet", "description": "A small database environment for MongoHQ.", "name": "Juliet", "current-event": null}, {"url": "http://status.mongohq.com/api/v1/services/kate", "id": "kate", "description": "MongoDB", "name": "Kate", "current-event": {"status": {"description": "The service is up", "level": "NORMAL", "url": "http://status.mongohq.com/api/v1/statuses/up", "image": "http://status.mongohq.com/images/status/tick-circle.png", "id": "up", "name": "Up"}, "url": "http://status.mongohq.com/api/v1/services/kate/events/ag5tb25nb2hxLXN0YXR1c3INCxIFRXZlbnQYodoWDA", "timestamp": "Tue, 23 Apr 2013 05:46:09 GMT", "sid": "ag5tb25nb2hxLXN0YXR1c3INCxIFRXZlbnQYodoWDA", "message": "kate.member1 is recovered and replica sets are running at full health.", "informational": false}}, {"url": "http://status.mongohq.com/api/v1/services/libby", "id": "libby", "description": "MongoDB Server", "name": "Libby", "current-event": null}, {"url": "http://status.mongohq.com/api/v1/services/linus", "id": "linus", "description": "Single server mongo host", "name": "Linus", "current-event": {"status": {"description": "The service is up", "level": "NORMAL", "url": "http://status.mongohq.com/api/v1/statuses/up", "image": "http://status.mongohq.com/images/status/tick-circle.png", "id": "up", "name": "Up"}, "url": "http://status.mongohq.com/api/v1/services/linus/events/ag5tb25nb2hxLXN0YXR1c3INCxIFRXZlbnQYkYYYDA", "timestamp": "Fri, 10 May 2013 23:36:21 GMT", "sid": "ag5tb25nb2hxLXN0YXR1c3INCxIFRXZlbnQYkYYYDA", "message": "Server is now fully recovered", "informational": false}}, {"url": "http://status.mongohq.com/api/v1/services/locke", "id": "locke", "description": "MongoDB Server", "name": "Locke", "current-event": {"status": {"description": "The service is up", "level": "NORMAL", "url": "http://status.mongohq.com/api/v1/statuses/up", "image": "http://status.mongohq.com/images/status/tick-circle.png", "id": "up", "name": "Up"}, "url": "http://status.mongohq.com/api/v1/services/locke/events/ag5tb25nb2hxLXN0YXR1c3INCxIFRXZlbnQYs8MODA", "timestamp": "Thu, 16 Aug 2012 17:57:23 GMT", "sid": "ag5tb25nb2hxLXN0YXR1c3INCxIFRXZlbnQYs8MODA", "message": "All systems operational.", "informational": false}}, {"url": "http://status.mongohq.com/api/v1/services/mars", "id": "mars", "description": "MongoHQ Small database environment.", "name": "Mars", "current-event": null}, {"url": "http://status.mongohq.com/api/v1/services/mongohq-api", "id": "mongohq-api", "description": "REST API for accessing MongoHQ", "name": "MongoHQ API", "current-event": {"status": {"description": "The service is up", "level": "NORMAL", "url": "http://status.mongohq.com/api/v1/statuses/up", "image": "http://status.mongohq.com/images/status/tick-circle.png", "id": "up", "name": "Up"}, "url": "http://status.mongohq.com/api/v1/services/mongohq-api/events/ag5tb25nb2hxLXN0YXR1c3INCxIFRXZlbnQYwZQODA", "timestamp": "Sat, 30 Jun 2012 11:02:48 GMT", "sid": "ag5tb25nb2hxLXN0YXR1c3INCxIFRXZlbnQYwZQODA", "message": "Website is fully recovered", "informational": false}}, {"url": "http://status.mongohq.com/api/v1/services/mongohq-website", "id": "mongohq-website", "description": "The Web frontend to MongoHQ", "name": "MongoHQ Website", "current-event": {"status": {"description": "The service is up", "level": "NORMAL", "url": "http://status.mongohq.com/api/v1/statuses/up", "image": "http://status.mongohq.com/images/status/tick-circle.png", "id": "up", "name": "Up"}, "url": "http://status.mongohq.com/api/v1/services/mongohq-website/events/ag5tb25nb2hxLXN0YXR1c3INCxIFRXZlbnQYyZ0YDA", "timestamp": "Sun, 12 May 2013 19:09:53 GMT", "sid": "ag5tb25nb2hxLXN0YXR1c3INCxIFRXZlbnQYyZ0YDA", "message": "All clear, website is responding normally now", "informational": false}}, {"url": "http://status.mongohq.com/api/v1/services/orchid", "id": "orchid", "description": "Our Orchid Environment. Currently in beta.", "name": "Orchid", "current-event": {"status": {"description": "The service is up", "level": "NORMAL", "url": "http://status.mongohq.com/api/v1/statuses/up", "image": "http://status.mongohq.com/images/status/tick-circle.png", "id": "up", "name": "Up"}, "url": "http://status.mongohq.com/api/v1/services/orchid/events/ag5tb25nb2hxLXN0YXR1c3INCxIFRXZlbnQYo-kRDA", "timestamp": "Mon, 22 Oct 2012 23:48:49 GMT", "sid": "ag5tb25nb2hxLXN0YXR1c3INCxIFRXZlbnQYo-kRDA", "message": "Environment is fully restored.", "informational": false}}, {"url": "http://status.mongohq.com/api/v1/services/pearl", "id": "pearl", "description": "MongoDB Server", "name": "Pearl", "current-event": {"status": {"description": "The service is up", "level": "NORMAL", "url": "http://status.mongohq.com/api/v1/statuses/up", "image": "http://status.mongohq.com/images/status/tick-circle.png", "id": "up", "name": "Up"}, "url": "http://status.mongohq.com/api/v1/services/pearl/events/ag5tb25nb2hxLXN0YXR1c3INCxIFRXZlbnQY8ewVDA", "timestamp": "Tue, 09 Apr 2013 04:52:34 GMT", "sid": "ag5tb25nb2hxLXN0YXR1c3INCxIFRXZlbnQY8ewVDA", "message": "Maintenance completed.", "informational": false}}, {"url": "http://status.mongohq.com/api/v1/services/penny", "id": "penny", "description": "MongoDB Server", "name": "Penny", "current-event": {"status": {"description": "The service is up", "level": "NORMAL", "url": "http://status.mongohq.com/api/v1/statuses/up", "image": "http://status.mongohq.com/images/status/tick-circle.png", "id": "up", "name": "Up"}, "url": "http://status.mongohq.com/api/v1/services/penny/events/ag5tb25nb2hxLXN0YXR1c3INCxIFRXZlbnQYma0YDA", "timestamp": "Sun, 12 May 2013 19:47:48 GMT", "sid": "ag5tb25nb2hxLXN0YXR1c3INCxIFRXZlbnQYma0YDA", "message": "Server is back online, and all mongo processes are functioning normally", "informational": false}}, {"url": "http://status.mongohq.com/api/v1/services/polarbear", "id": "polarbear", "description": "MongoDB Server", "name": "Polarbear", "current-event": {"status": {"description": "The service is up", "level": "NORMAL", "url": "http://status.mongohq.com/api/v1/statuses/up", "image": "http://status.mongohq.com/images/status/tick-circle.png", "id": "up", "name": "Up"}, "url": "http://status.mongohq.com/api/v1/services/polarbear/events/ag5tb25nb2hxLXN0YXR1c3INCxIFRXZlbnQYsasWDA", "timestamp": "Tue, 16 Apr 2013 03:26:47 GMT", "sid": "ag5tb25nb2hxLXN0YXR1c3INCxIFRXZlbnQYsasWDA", "message": "polarbear.member0 is fully restored.", "informational": false}}, {"url": "http://status.mongohq.com/api/v1/services/rose", "id": "rose", "description": "Rose is an environment for our Small databases.", "name": "Rose", "current-event": {"status": {"description": "The service is up", "level": "NORMAL", "url": "http://status.mongohq.com/api/v1/statuses/up", "image": "http://status.mongohq.com/images/status/tick-circle.png", "id": "up", "name": "Up"}, "url": "http://status.mongohq.com/api/v1/services/rose/events/ag5tb25nb2hxLXN0YXR1c3INCxIFRXZlbnQY2Y8NDA", "timestamp": "Fri, 15 Jun 2012 05:12:08 GMT", "sid": "ag5tb25nb2hxLXN0YXR1c3INCxIFRXZlbnQY2Y8NDA", "message": "All systems operational.", "informational": false}}, {"url": "http://status.mongohq.com/api/v1/services/sawyer", "id": "sawyer", "description": "MongoDB Server", "name": "Sawyer", "current-event": {"status": {"description": "The service is up", "level": "NORMAL", "url": "http://status.mongohq.com/api/v1/statuses/up", "image": "http://status.mongohq.com/images/status/tick-circle.png", "id": "up", "name": "Up"}, "url": "http://status.mongohq.com/api/v1/services/sawyer/events/ag5tb25nb2hxLXN0YXR1c3INCxIFRXZlbnQYod0VDA", "timestamp": "Tue, 09 Apr 2013 04:20:44 GMT", "sid": "ag5tb25nb2hxLXN0YXR1c3INCxIFRXZlbnQYod0VDA", "message": "Maintenance is complete.", "informational": false}}, {"url": "http://status.mongohq.com/api/v1/services/sayid", "id": "sayid", "description": "MongoDB", "name": "Sayid", "current-event": null}, {"url": "http://status.mongohq.com/api/v1/services/smoke-0", "id": "smoke-0", "description": "MongoDB", "name": "Smoke.0", "current-event": null}, {"url": "http://status.mongohq.com/api/v1/services/smoke-1", "id": "smoke-1", "description": "MongoDB", "name": "Smoke.1", "current-event": null}, {"url": "http://status.mongohq.com/api/v1/services/smoke-3", "id": "smoke-3", "description": "Mongo SSD replica set", "name": "Smoke.3", "current-event": {"status": {"description": "The service is up", "level": "NORMAL", "url": "http://status.mongohq.com/api/v1/statuses/up", "image": "http://status.mongohq.com/images/status/tick-circle.png", "id": "up", "name": "Up"}, "url": "http://status.mongohq.com/api/v1/services/smoke-3/events/ag5tb25nb2hxLXN0YXR1c3INCxIFRXZlbnQYqYEXDA", "timestamp": "Tue, 23 Apr 2013 17:26:47 GMT", "sid": "ag5tb25nb2hxLXN0YXR1c3INCxIFRXZlbnQYqYEXDA", "message": "smoke.3 is running normally.", "informational": false}}, {"url": "http://status.mongohq.com/api/v1/services/smoke-4", "id": "smoke-4", "description": "MongoHQ SSD Replica Set.", "name": "Smoke.4", "current-event": {"status": {"description": "The service is up", "level": "NORMAL", "url": "http://status.mongohq.com/api/v1/statuses/up", "image": "http://status.mongohq.com/images/status/tick-circle.png", "id": "up", "name": "Up"}, "url": "http://status.mongohq.com/api/v1/services/smoke-4/events/ag5tb25nb2hxLXN0YXR1c3INCxIFRXZlbnQYiuIWDA", "timestamp": "Tue, 23 Apr 2013 18:12:18 GMT", "sid": "ag5tb25nb2hxLXN0YXR1c3INCxIFRXZlbnQYiuIWDA", "message": "Full connectivity restored.", "informational": false}}, {"url": "http://status.mongohq.com/api/v1/services/staff", "id": "staff", "description": "staff.mongohq.com", "name": "Staff", "current-event": {"status": {"description": "The service is up", "level": "NORMAL", "url": "http://status.mongohq.com/api/v1/statuses/up", "image": "http://status.mongohq.com/images/status/tick-circle.png", "id": "up", "name": "Up"}, "url": "http://status.mongohq.com/api/v1/services/staff/events/ag5tb25nb2hxLXN0YXR1c3INCxIFRXZlbnQY08oWDA", "timestamp": "Thu, 25 Apr 2013 07:44:41 GMT", "sid": "ag5tb25nb2hxLXN0YXR1c3INCxIFRXZlbnQY08oWDA", "message": "Environment is fully recovered and healthy", "informational": false}}, {"url": "http://status.mongohq.com/api/v1/services/sun", "id": "sun", "description": "MongoDB Server", "name": "Sun", "current-event": {"status": {"description": "The service is up", "level": "NORMAL", "url": "http://status.mongohq.com/api/v1/statuses/up", "image": "http://status.mongohq.com/images/status/tick-circle.png", "id": "up", "name": "Up"}, "url": "http://status.mongohq.com/api/v1/services/sun/events/ag5tb25nb2hxLXN0YXR1c3INCxIFRXZlbnQYk5sRDA", "timestamp": "Mon, 22 Oct 2012 23:49:33 GMT", "sid": "ag5tb25nb2hxLXN0YXR1c3INCxIFRXZlbnQYk5sRDA", "message": "Environment is fully restorted.", "informational": false}}, {"url": "http://status.mongohq.com/api/v1/services/swan", "id": "swan", "description": "MongoDB Server", "name": "Swan", "current-event": {"status": {"description": "The service is up", "level": "NORMAL", "url": "http://status.mongohq.com/api/v1/statuses/up", "image": "http://status.mongohq.com/images/status/tick-circle.png", "id": "up", "name": "Up"}, "url": "http://status.mongohq.com/api/v1/services/swan/events/ag5tb25nb2hxLXN0YXR1c3INCxIFRXZlbnQY6tERDA", "timestamp": "Mon, 22 Oct 2012 23:10:53 GMT", "sid": "ag5tb25nb2hxLXN0YXR1c3INCxIFRXZlbnQY6tERDA", "message": "Performance has resumed to normal on the Swan environment.", "informational": false}}, {"url": "http://status.mongohq.com/api/v1/services/tempest", "id": "tempest", "description": "Tempest is an environment for our Large databases.", "name": "Tempest", "current-event": {"status": {"description": "The service is up", "level": "NORMAL", "url": "http://status.mongohq.com/api/v1/statuses/up", "image": "http://status.mongohq.com/images/status/tick-circle.png", "id": "up", "name": "Up"}, "url": "http://status.mongohq.com/api/v1/services/tempest/events/ag5tb25nb2hxLXN0YXR1c3INCxIFRXZlbnQYiv0NDA", "timestamp": "Sat, 30 Jun 2012 10:01:05 GMT", "sid": "ag5tb25nb2hxLXN0YXR1c3INCxIFRXZlbnQYiv0NDA", "message": "All databases are accessible and operating normally", "informational": false}}, {"url": "http://status.mongohq.com/api/v1/services/vincent", "id": "vincent", "description": "The Vincent MongoDB environment", "name": "Vincent", "current-event": {"status": {"description": "The service is up", "level": "NORMAL", "url": "http://status.mongohq.com/api/v1/statuses/up", "image": "http://status.mongohq.com/images/status/tick-circle.png", "id": "up", "name": "Up"}, "url": "http://status.mongohq.com/api/v1/services/vincent/events/ag5tb25nb2hxLXN0YXR1c3INCxIFRXZlbnQYy7IRDA", "timestamp": "Tue, 23 Oct 2012 09:11:06 GMT", "sid": "ag5tb25nb2hxLXN0YXR1c3INCxIFRXZlbnQYy7IRDA", "message": "Connectivity has been restored. All systems operational.", "informational": false}}, {"url": "http://status.mongohq.com/api/v1/services/walt", "id": "walt", "description": "US East Large.", "name": "Walt", "current-event": {"status": {"description": "The service is up", "level": "NORMAL", "url": "http://status.mongohq.com/api/v1/statuses/up", "image": "http://status.mongohq.com/images/status/tick-circle.png", "id": "up", "name": "Up"}, "url": "http://status.mongohq.com/api/v1/services/walt/events/ag5tb25nb2hxLXN0YXR1c3INCxIFRXZlbnQYqYoUDA", "timestamp": "Mon, 25 Feb 2013 04:09:16 GMT", "sid": "ag5tb25nb2hxLXN0YXR1c3INCxIFRXZlbnQYqYoUDA", "message": "Updates are now complete and the system is fully operational.", "informational": false}}, {"url": "http://status.mongohq.com/api/v1/services/workman-0", "id": "workman-0", "description": "MongoDB", "name": "Workman.0", "current-event": null}, {"url": "http://status.mongohq.com/api/v1/services/workman-1", "id": "workman-1", "description": "MongoDB", "name": "Workman.1", "current-event": null}]}